LICENSE.txt
MANIFEST.in
README.md
setup.py
django_servee_tinymce.egg-info/PKG-INFO
django_servee_tinymce.egg-info/SOURCES.txt
django_servee_tinymce.egg-info/dependency_links.txt
django_servee_tinymce.egg-info/not-zip-safe
django_servee_tinymce.egg-info/top_level.txt
servee_tinymce/.DS_Store
servee_tinymce/__init__.py
servee_tinymce/__init__.pyc
servee_tinymce/models.py
servee_tinymce/models.pyc
servee_tinymce/static/.DS_Store
servee_tinymce/static/servee/.DS_Store
servee_tinymce/static/servee/wysiwyg/.DS_Store
servee_tinymce/static/servee/wysiwyg/js/tinymce.js
servee_tinymce/static/tinymce/.DS_Store
servee_tinymce/static/tinymce/changelog.txt
servee_tinymce/static/tinymce/jscripts/.DS_Store
servee_tinymce/static/tinymce/jscripts/tiny_mce/jquery.tinymce.js
servee_tinymce/static/tinymce/jscripts/tiny_mce/license.txt
servee_tinymce/static/tinymce/jscripts/tiny_mce/tiny_mce.js
servee_tinymce/static/tinymce/jscripts/tiny_mce/tiny_mce_popup.js
servee_tinymce/static/tinymce/jscripts/tiny_mce/tiny_mce_src.js
servee_tinymce/static/tinymce/jscripts/tiny_mce/langs/en.js
servee_tinymce/static/tinymce/jscripts/tiny_mce/plugins/advhr/editor_plugin.js
servee_tinymce/static/tinymce/jscripts/tiny_mce/plugins/advhr/editor_plugin_src.js
servee_tinymce/static/tinymce/jscripts/tiny_mce/plugins/advhr/rule.htm
servee_tinymce/static/tinymce/jscripts/tiny_mce/plugins/advhr/css/advhr.css
servee_tinymce/static/tinymce/jscripts/tiny_mce/plugins/advhr/js/rule.js
servee_tinymce/static/tinymce/jscripts/tiny_mce/plugins/advhr/langs/en_dlg.js
servee_tinymce/static/tinymce/jscripts/tiny_mce/plugins/advimage/editor_plugin.js
servee_tinymce/static/tinymce/jscripts/tiny_mce/plugins/advimage/editor_plugin_src.js
servee_tinymce/static/tinymce/jscripts/tiny_mce/plugins/advimage/image.htm
servee_tinymce/static/tinymce/jscripts/tiny_mce/plugins/advimage/css/advimage.css
servee_tinymce/static/tinymce/jscripts/tiny_mce/plugins/advimage/img/sample.gif
servee_tinymce/static/tinymce/jscripts/tiny_mce/plugins/advimage/js/image.js
servee_tinymce/static/tinymce/jscripts/tiny_mce/plugins/advimage/langs/en_dlg.js
servee_tinymce/static/tinymce/jscripts/tiny_mce/plugins/advlink/editor_plugin.js
